{
  "project_info": {
    "project_number": "318837877708",
    "project_id": "prueba-438c5",
    "storage_bucket": "prueba-438c5.appspot.com"
  },
  "client": [
    {
      "client_info": {
        "mobilesdk_app_id": "1:318837877708:android:35b7966f44739ad4ab4b69",
        "android_client_info": {
          "package_name": "com.example.fire_base_evento"
        }
      },
      "oauth_client": [
        {
          "client_id": "318837877708-mim284m6fu5p82shqdckh7sf4i5298b3.apps.googleusercontent.com",
          "client_type": 3
        }
      ],
      "api_key": [
        {
          "current_key": "AIzaSyCRg6I7FLiL1Zyo5iLnr_T8njdHOPa5EQ0"
        }
      ],
      "services": {
        "appinvite_service": {
          "other_platform_oauth_client": [
            {
              "client_id": "318837877708-mim284m6fu5p82shqdckh7sf4i5298b3.apps.googleusercontent.com",
              "client_type": 3
            }
          ]
        }
      }
    }
  ],
  "configuration_version": "1"
}